frest/__init__.py
frest/core.py
flask_frest-0.1.3.dist-info/METADATA
flask_frest-0.1.3.dist-info/WHEEL
flask_frest-0.1.3.dist-info/top_level.txt
flask_frest-0.1.3.dist-info/RECORD
