Metadata-Version: 2.1
Name: flask-frest
Version: 0.1.3
Summary: make your flask app become restful and modern
Requires-Python: >=3.12
Requires-Dist: flask >=3.0.3
Requires-Dist: pydantic >=2.9.2
